segmlab/__init__.py
segmlab/model_downloader.py
segmlab/model_loader.py
segmlab/segment.py
segmlab/segmenter.py
segmlab/utils.py
segmlab-0.1.3.dist-info/METADATA
segmlab-0.1.3.dist-info/WHEEL
segmlab-0.1.3.dist-info/top_level.txt
segmlab-0.1.3.dist-info/RECORD
